{"trial_id": "0203", "hyperparameters": {"space": [{"class_name": "Int", "config": {"name": "units_1", "default": null, "conditions": [], "min_value": 128, "max_value": 160, "step": 32, "sampling": "linear"}}, {"class_name": "Int", "config": {"name": "units_2", "default": null, "conditions": [], "min_value": 64, "max_value": 128, "step": 32, "sampling": "linear"}}, {"class_name": "Int", "config": {"name": "units_3", "default": null, "conditions": [], "min_value": 32, "max_value": 64, "step": 16, "sampling": "linear"}}, {"class_name": "Float", "config": {"name": "learning_rate", "default": 0.0005, "conditions": [], "min_value": 0.0001, "max_value": 0.01, "step": null, "sampling": "log"}}], "values": {"units_1": 160, "units_2": 128, "units_3": 32, "learning_rate": 0.002998003302664412, "tuner/epochs": 50, "tuner/initial_epoch": 17, "tuner/bracket": 3, "tuner/round": 2, "tuner/trial_id": "0200"}}, "metrics": {"metrics": {"loss": {"direction": "min", "observations": [{"value": [446750704.0], "step": 3}]}, "mae": {"direction": "min", "observations": [{"value": [14845.88525390625], "step": 3}]}, "mse": {"direction": "min", "observations": [{"value": [446750704.0], "step": 3}]}, "val_loss": {"direction": "min", "observations": [{"value": [3481004160.0], "step": 3}]}, "val_mae": {"direction": "min", "observations": [{"value": [29865.4609375], "step": 3}]}, "val_mse": {"direction": "min", "observations": [{"value": [3481004160.0], "step": 3}]}}}, "score": 3481004160.0, "best_step": 3, "status": "COMPLETED", "message": null}